swesmith/__init__.py
swesmith/constants.py
swesmith/bug_gen/__init__.py
swesmith/bug_gen/collect_patches.py
swesmith/bug_gen/get_cost.py
swesmith/bug_gen/utils.py
swesmith/bug_gen/adapters/__init__.py
swesmith/bug_gen/adapters/c.py
swesmith/bug_gen/adapters/c_sharp.py
swesmith/bug_gen/adapters/cpp.py
swesmith/bug_gen/adapters/golang.py
swesmith/bug_gen/adapters/java.py
swesmith/bug_gen/adapters/javascript.py
swesmith/bug_gen/adapters/php.py
swesmith/bug_gen/adapters/python.py
swesmith/bug_gen/adapters/ruby.py
swesmith/bug_gen/adapters/rust.py
swesmith/bug_gen/combine/__init__.py
swesmith/bug_gen/combine/same_file.py
swesmith/bug_gen/combine/same_module.py
swesmith/bug_gen/llm/__init__.py
swesmith/bug_gen/llm/modify.py
swesmith/bug_gen/llm/rewrite.py
swesmith/bug_gen/llm/utils.py
swesmith/bug_gen/mirror/__init__.py
swesmith/bug_gen/mirror/generate.py
swesmith/bug_gen/mirror/prompts.py
swesmith/bug_gen/mirror/collect/__init__.py
swesmith/bug_gen/mirror/collect/__main__.py
swesmith/bug_gen/mirror/collect/build_dataset.py
swesmith/bug_gen/mirror/collect/print_pulls.py
swesmith/bug_gen/mirror/collect/utils.py
swesmith/bug_gen/procedural/__init__.py
swesmith/bug_gen/procedural/base.py
swesmith/bug_gen/procedural/generate.py
swesmith/bug_gen/procedural/golang/__init__.py
swesmith/bug_gen/procedural/golang/base.py
swesmith/bug_gen/procedural/golang/control_flow.py
swesmith/bug_gen/procedural/golang/operations.py
swesmith/bug_gen/procedural/golang/remove.py
swesmith/bug_gen/procedural/python/__init__.py
swesmith/bug_gen/procedural/python/base.py
swesmith/bug_gen/procedural/python/classes.py
swesmith/bug_gen/procedural/python/control_flow.py
swesmith/bug_gen/procedural/python/operations.py
swesmith/bug_gen/procedural/python/remove.py
swesmith/bug_gen/procedural/rust/__init__.py
swesmith/bug_gen/procedural/rust/operations.py
swesmith/build_repo/__init__.py
swesmith/build_repo/create_images.py
swesmith/build_repo/download_images.py
swesmith/build_repo/try_install_py.py
swesmith-0.0.7.dist-info/licenses/LICENSE
swesmith-0.0.7.dist-info/METADATA
swesmith-0.0.7.dist-info/WHEEL
swesmith-0.0.7.dist-info/top_level.txt
swesmith-0.0.7.dist-info/RECORD
