Metadata-Version: 2.4
Name: swesmith
Version: 0.0.7
Summary: The official SWE-smith package - A toolkit for generating software engineering training data at scale.
Author-email: John Yang <byjohnyang@gmail.com>
License: MIT License
Project-URL: Documentation, https://github.com/SWE-bench/SWE-smith
Project-URL: Bug Reports, https://github.com/SWE-bench/SWE-smith/issues
Project-URL: Source Code, https://github.com/SWE-bench/SWE-smith
Project-URL: Website, https://swesmith.com
Keywords: nlp,benchmark,code
Classifier: Programming Language :: Python :: 3.10
Classifier: Programming Language :: Python :: 3.11
Classifier: Programming Language :: Python :: 3 :: Only
Classifier: License :: OSI Approved :: MIT License
Classifier: Operating System :: OS Independent
Requires-Python: >=3.10
License-File: LICENSE
Requires-Dist: astor
Requires-Dist: datasets
Requires-Dist: docker
Requires-Dist: ghapi
Requires-Dist: libcst
Requires-Dist: litellm
Requires-Dist: matplotlib
Requires-Dist: modal
Requires-Dist: openai
Requires-Dist: pre-commit
Requires-Dist: python-dotenv
Requires-Dist: rich
Requires-Dist: sglang
Requires-Dist: sparklines
Requires-Dist: swebench
Requires-Dist: tiktoken
Requires-Dist: tqdm
Requires-Dist: tree-sitter>=0.25
Requires-Dist: tree-sitter-c
Requires-Dist: tree-sitter-cpp
Requires-Dist: tree-sitter-c-sharp
Requires-Dist: tree-sitter-go
Requires-Dist: tree-sitter-javascript
Requires-Dist: tree-sitter-java
Requires-Dist: tree-sitter-ruby
Requires-Dist: tree-sitter-rust
Requires-Dist: unidiff
Requires-Dist: textual
Requires-Dist: tree-sitter-php>=0.23.11
Provides-Extra: docs
Requires-Dist: mkdocs; extra == "docs"
Requires-Dist: mkdocs-material; extra == "docs"
Requires-Dist: mkdocs-glightbox; extra == "docs"
Requires-Dist: mkdocs-include-markdown-plugin; extra == "docs"
Requires-Dist: mkdocstrings[python]>=0.18; extra == "docs"
Requires-Dist: mike; extra == "docs"
Provides-Extra: test
Requires-Dist: pytest; extra == "test"
Requires-Dist: pytest-cov; extra == "test"
Dynamic: license-file
